{"cameraMode":{"drawMode":0,"name":"Shaded","section":"Shading Mode"},"sceneLighting":true,"audioPlay":false,"sceneViewState":{"m_AlwaysRefresh":false,"showFog":true,"showSkybox":true,"showFlares":true,"showImageEffects":true,"showParticleSystems":true,"showVisualEffectGraphs":true,"m_FxEnabled":true},"in2DMode":false,"pivot":{"x":-0.6175851821899414,"y":0.4775065779685974,"z":2.013248920440674},"rotation":{"x":-0.06325027346611023,"y":0.9367383122444153,"z":-0.24719633162021638,"w":-0.23967291414737702},"size":1.7589360475540162,"orthographic":false}